QuizzingApp/__init__.py
QuizzingApp/__main__.py
QuizzingApp/errors.py
QuizzingApp/main.py
QuizzingApp/questionbase/question.py
QuizzingApp/questionbase/question_manager.py
QuizzingApp/quizsession/result.py
QuizzingApp/quizsession/session.py
QuizzingApp/userprofile/manage_user.py
QuizzingApp/userprofile/user.py
quizzingapppackage-0.1.0.dist-info/licenses/LICENSE
quizzingapppackage-0.1.0.dist-info/METADATA
quizzingapppackage-0.1.0.dist-info/WHEEL
quizzingapppackage-0.1.0.dist-info/top_level.txt
quizzingapppackage-0.1.0.dist-info/RECORD
