Metadata-Version: 2.4
Name: QuizzingAppPackage
Version: 0.1.0
Summary: A command-line quizzing application
Author-email: Jingtao Yang <yangjingtaoitb@gmail.com>
Project-URL: Homepage, https://github.com/ubco-mds-2025-labs/project-step-3-andrewyang0620
Classifier: Programming Language :: Python :: 3
Classifier: License :: OSI Approved :: MIT License
Classifier: Operating System :: OS Independent
Requires-Python: >=3.9
License-File: LICENSE
Dynamic: license-file
